odoo/addons/crm_partner_company_group/README.rst
odoo/addons/crm_partner_company_group/__init__.py
odoo/addons/crm_partner_company_group/__manifest__.py
odoo/addons/crm_partner_company_group/i18n/crm_partner_company_group.pot
odoo/addons/crm_partner_company_group/i18n/es.po
odoo/addons/crm_partner_company_group/i18n/it.po
odoo/addons/crm_partner_company_group/i18n/pt_BR.po
odoo/addons/crm_partner_company_group/i18n/zh_CN.po
odoo/addons/crm_partner_company_group/models/__init__.py
odoo/addons/crm_partner_company_group/models/crm_lead.py
odoo/addons/crm_partner_company_group/readme/CONTRIBUTORS.md
odoo/addons/crm_partner_company_group/readme/CREDITS.md
odoo/addons/crm_partner_company_group/readme/DESCRIPTION.md
odoo/addons/crm_partner_company_group/static/description/icon.png
odoo/addons/crm_partner_company_group/static/description/index.html
odoo/addons/crm_partner_company_group/views/opportunity_view.xml
odoo_addon_crm_partner_company_group-18.0.1.1.0.dist-info/METADATA
odoo_addon_crm_partner_company_group-18.0.1.1.0.dist-info/WHEEL
odoo_addon_crm_partner_company_group-18.0.1.1.0.dist-info/top_level.txt
odoo_addon_crm_partner_company_group-18.0.1.1.0.dist-info/RECORD
